.gitignore
LICENSE.md
MANIFEST.in
README.md
requirements.txt
setup.cfg
setup.py
update_docs.sh
docs/Makefile
docs/make.bat
docs/source/conf.py
docs/source/index.rst
serasa/__init__.py
serasa.egg-info/PKG-INFO
serasa.egg-info/SOURCES.txt
serasa.egg-info/dependency_links.txt
serasa.egg-info/requires.txt
serasa.egg-info/top_level.txt
tests/__init__.py
tests/test_sample.py